HumanActivityRecognition/__init__.py
HumanActivityRecognition-0.1.dist-info/METADATA
HumanActivityRecognition-0.1.dist-info/WHEEL
HumanActivityRecognition-0.1.dist-info/top_level.txt
HumanActivityRecognition-0.1.dist-info/RECORD
