Metadata-Version: 2.1
Name: HumanActivityRecognition
Version: 0.1
Summary: Package to recognize Human Activity Recognition
Home-page: UNKNOWN
Author: Salma
Author-email: ssalma3157@outlook.com
License: UNKNOWN
Platform: UNKNOWN
Classifier: Programming Language :: Python :: 3
Classifier: License :: OSI Approved :: MIT License
Requires-Python: >=3.6
